mitepid/__init__.py
mitepid/epid_sim.py
mitepid/models.py
mitepid/plots.py
mitepid/policies.py
mitepid/utils.py
mitepid/Optimised_B/B_opt_SEIR_I5_E4p6.mat
mitepid/Optimised_B/B_opt_SEIR_Ti_10_R0_2.95.mat
mitepid/Optimised_B/B_opt_SEIR_Ti_11_R0_2.95.mat
mitepid/Optimised_B/B_opt_SEIR_Ti_12_R0_2.95.mat
mitepid/Optimised_B/B_opt_SEIR_Ti_13_R0_2.95.mat
mitepid/Optimised_B/B_opt_SEIR_Ti_14_R0_2.95.mat
mitepid/Optimised_B/B_opt_SEIR_Ti_15_R0_2.95.mat
mitepid/Optimised_B/B_opt_SEIR_Ti_15_R0_2.95_b.mat
mitepid/Optimised_B/B_opt_SEIR_Ti_5_R0_2.05.mat
mitepid/Optimised_B/B_opt_SEIR_Ti_5_R0_2.15.mat
mitepid/Optimised_B/B_opt_SEIR_Ti_5_R0_2.25.mat
mitepid/Optimised_B/B_opt_SEIR_Ti_5_R0_2.35.mat
mitepid/Optimised_B/B_opt_SEIR_Ti_5_R0_2.45.mat
mitepid/Optimised_B/B_opt_SEIR_Ti_5_R0_2.55.mat
mitepid/Optimised_B/B_opt_SEIR_Ti_5_R0_2.65.mat
mitepid/Optimised_B/B_opt_SEIR_Ti_5_R0_2.75.mat
mitepid/Optimised_B/B_opt_SEIR_Ti_5_R0_2.85.mat
mitepid/Optimised_B/B_opt_SEIR_Ti_5_R0_2.95.mat
mitepid/Optimised_B/B_opt_SEIR_Ti_5_R0_3.05.mat
mitepid/Optimised_B/B_opt_SEIR_Ti_5_R0_3.15.mat
mitepid/Optimised_B/B_opt_SEIR_Ti_5_R0_3.25.mat
mitepid/Optimised_B/B_opt_SEIR_Ti_5_R0_3.35.mat
mitepid/Optimised_B/B_opt_SEIR_Ti_5_R0_3.45.mat
mitepid/Optimised_B/B_opt_SEIR_Ti_5_R0_3.55.mat
mitepid/Optimised_B/B_opt_SEIR_Ti_5_R0_3.65.mat
mitepid/Optimised_B/B_opt_SEIR_Ti_5_R0_3.75.mat
mitepid/Optimised_B/B_opt_SEIR_Ti_5_R0_3.85.mat
mitepid/Optimised_B/B_opt_SEIR_Ti_5_R0_3.95.mat
mitepid/Optimised_B/B_opt_SEIR_Ti_6_R0_2.95.mat
mitepid/Optimised_B/B_opt_SEIR_Ti_7_R0_2.95.mat
mitepid/Optimised_B/B_opt_SEIR_Ti_8_R0_2.95.mat
mitepid/Optimised_B/B_opt_SEIR_Ti_9_R0_2.95.mat
mitepid/Optimised_B/B_opt_SIR_I9p6.mat
mitepid/Optimised_B/B_opt_SIS_I9p6.mat
MiTepid-0.0.5.dist-info/LICENSE
MiTepid-0.0.5.dist-info/METADATA
MiTepid-0.0.5.dist-info/WHEEL
MiTepid-0.0.5.dist-info/top_level.txt
MiTepid-0.0.5.dist-info/RECORD
