Metadata-Version: 2.1
Name: MiTepid
Version: 0.0.5
Summary: MiTepid_sim: A repository to simulate the spread of COVID-19 in any population with a known age-structure, Made in Tuebingen.
Home-page: https://github.com/vahid-sb/MiTepid_sim
Author: Vahid Samadi Bokharaie
Author-email: vahid.bokharaie@protonmail.com
License: GNU Version 3
Platform: UNKNOWN
Classifier: Development Status :: 2 - Pre-Alpha
Classifier: License :: OSI Approved :: GNU General Public License v3 (GPLv3)
Classifier: Programming Language :: Python
Classifier: Programming Language :: Python :: 3.8
Requires-Dist: numpy
Requires-Dist: scipy
Requires-Dist: matplotlib
Requires-Dist: pathlib
